Metadata-Version: 1.1
Name: tabellarius
Version: 2.0.1
Summary: A mail-sorting tool that is less annoying
Home-page: https://github.com/bechtoldt/tabellarius
Author: Arnold Bechtoldt
Author-email: mail@arnoldbechtoldt.com
License: Apache 2.0
Platform: UNKNOWN
Classifier: License :: OSI Approved :: Apache Software License
Classifier: Programming Language :: Python
Classifier: Programming Language :: Python :: 3
Classifier: Programming Language :: Python :: 3.4
Classifier: Programming Language :: Python :: 3.5
Classifier: Programming Language :: Python :: 3.6
Classifier: Programming Language :: Python :: 3.7
Classifier: Topic :: Communications :: Email :: Filters
